{
  "locationName": "Star Station",
  "padSize": 65.0,
  "padFriction": 0.0002,
  "airFriction": 0.0020,
  "airDensity": 0.0001,
  "airRotateForce": 0.0001,
  "airMinForce": 1,
  "airMaxForce": 3,
  "airDynamics": 0.1,
  "gravity": 0.25,
  "texturesNames": {
    "pad": "CyberCityBackground/Podpory_skocznia1.png",
    "background": {
      "0": "earth-layer0.png",
      "1": "earth-layer1.png"
    }
  },
  "jumpStartPoint": 1500,
  "padPullingPoints": [
    {"x":416.0,"y":708.0},
    {"x":1150.0,"y":1200.0},
    {"x":1600.0,"y":1450.0},
    {"x":1700.0,"y":1480.0},
    {"x":1900.0,"y":1510.0}
  ],
  "padShapeScalars": [
    {
      "x": 6000,
      "y": 2500
    }
  ]
}